{"cameraMode":{"drawMode":0,"name":"Shaded","section":"Shading Mode"},"sceneLighting":true,"audioPlay":false,"sceneViewState":{"m_AlwaysRefresh":false,"showFog":true,"showSkybox":true,"showFlares":true,"showImageEffects":true,"showParticleSystems":true,"showVisualEffectGraphs":true,"m_FxEnabled":true},"in2DMode":false,"pivot":{"x":17.18072509765625,"y":-88.48905944824219,"z":52.62864685058594},"rotation":{"x":0.5617415308952332,"y":0.2131650298833847,"z":-0.1525985300540924,"w":0.7846720218658447},"size":56.72278594970703,"orthographic":false}